tasteful/__init__.py
tasteful/authn/base/__init__.py
tasteful/authn/base/backend.py
tasteful/authn/base/middleware.py
tasteful/authn/base/user.py
tasteful/authn/jwks/__init__.py
tasteful/authn/jwks/middleware.py
tasteful/authn/jwks/user.py
tasteful/authn/oidc/__init__.py
tasteful/authn/oidc/backend.py
tasteful/authn/oidc/middleware.py
tasteful/authn/oidc/user.py
tasteful/authz/base/backend.py
tasteful/authz/base/middleware.py
tasteful/authz/oidc/backend.py
tasteful/authz/oidc/middleware.py
tasteful/authz/zitadel/backend.py
tasteful/authz/zitadel/middleware.py
tasteful/base_flavor/__init__.py
tasteful/base_flavor/base_config.py
tasteful/base_flavor/base_controller.py
tasteful/base_flavor/base_flavor.py
tasteful/base_flavor/base_service.py
tasteful/config.py
tasteful/containers/base_flavor_container.py
tasteful/containers/tasteful_container.py
tasteful/decorators/auth.py
tasteful/decorators/authz.py
tasteful/decorators/controller.py
tasteful/dependencies/__init__.py
tasteful/dependencies/graph.py
tasteful/exceptions/dependency_graph.py
tasteful/exceptions/injector.py
tasteful/logger/__init__.py
tasteful/logger/formatter/tasteful_formatter.py
tasteful/repositories/__init__.py
tasteful/repositories/base_repository.py
tasteful/repositories/sqlmodel_repository.py
tasteful/tasteful_application.py
tasteful-0.3.0.dist-info/METADATA
tasteful-0.3.0.dist-info/WHEEL
tasteful-0.3.0.dist-info/RECORD
